naacl_utils/__init__.py
naacl_utils/__main__.py
naacl_utils/version.py
naacl_utils-0.4.2.dist-info/LICENSE
naacl_utils-0.4.2.dist-info/METADATA
naacl_utils-0.4.2.dist-info/WHEEL
naacl_utils-0.4.2.dist-info/entry_points.txt
naacl_utils-0.4.2.dist-info/top_level.txt
naacl_utils-0.4.2.dist-info/RECORD
