Metadata-Version: 2.1
Name: naacl-utils
Version: 0.4.2
Home-page: https://github.com/naacl2022-reproducibility-track/naacl-utils
Author: Allen Institute for Artificial Intelligence
Author-email: petew@allenai.org
License: Apache
Classifier: Intended Audience :: Science/Research
Classifier: Development Status :: 3 - Alpha
Classifier: License :: OSI Approved :: Apache Software License
Classifier: Programming Language :: Python :: 3
Classifier: Topic :: Scientific/Engineering :: Artificial Intelligence
Requires-Python: >=3.7
License-File: LICENSE
Requires-Dist: requests
Requires-Dist: packaging
Requires-Dist: beaker-py (==0.2.8)
Requires-Dist: click (<8.1,>=8.0)
Requires-Dist: click-help-colors (<0.10,>=0.9.1)
Requires-Dist: rich (<12.1,>=12.0)
Provides-Extra: dev
Requires-Dist: flake8 ; extra == 'dev'
Requires-Dist: mypy (==0.942) ; extra == 'dev'
Requires-Dist: black (==22.3.0) ; extra == 'dev'
Requires-Dist: isort (==5.10.1) ; extra == 'dev'
Requires-Dist: pytest ; extra == 'dev'
Requires-Dist: twine (>=1.11.0) ; extra == 'dev'
Requires-Dist: setuptools ; extra == 'dev'
Requires-Dist: wheel ; extra == 'dev'
